AUTHORS
ChangeLog
LICENSE.md
MANIFEST.in
Makefile
README.md
requirements.txt
setup.cfg
setup.py
oftools/Main.py
oftools/__init__.py
oftools.egg-info/PKG-INFO
oftools.egg-info/SOURCES.txt
oftools.egg-info/dependency_links.txt
oftools.egg-info/entry_points.txt
oftools.egg-info/not-zip-safe
oftools.egg-info/pbr.json
oftools.egg-info/requires.txt
oftools.egg-info/top_level.txt